Converter.py
IO.py
Maintenance.py
Processor.py
Visualization.py
__init__.py
patch_encoder_models/__init__.py
patch_encoder_models/load.py
patch_encoder_models/local_ckpts.json
patch_encoder_models/model_zoo/__init__.py
patch_encoder_models/model_zoo/conchv1_5/__init__.py
patch_encoder_models/model_zoo/conchv1_5/conchv1_5.py
patch_encoder_models/model_zoo/ctranspath/__init__.py
patch_encoder_models/model_zoo/ctranspath/ctran.py
patch_encoder_models/utils/__init__.py
patch_encoder_models/utils/constants.py
patch_encoder_models/utils/transform_utils.py
segmentation_models/__init__.py
segmentation_models/load.py
segmentation_models/local_ckpts.json
slide_encoder_models/__init__.py
slide_encoder_models/load.py
slide_encoder_models/local_ckpts.json
slide_encoder_models/model_zoo/__init__.py
slide_encoder_models/model_zoo/reusable_blocks/ABMIL.py
slide_encoder_models/model_zoo/reusable_blocks/__init__.py
wsi_objects/CuCIMWSI.py
wsi_objects/ImageWSI.py
wsi_objects/OpenSlideWSI.py
wsi_objects/WSI.py
wsi_objects/WSIFactory.py
wsi_objects/WSIPatcher.py
wsi_objects/WSIPatcherDataset.py
wsi_objects/__init__.py
trident_test-0.1.1.dist-info/LICENSE
trident_test-0.1.1.dist-info/METADATA
trident_test-0.1.1.dist-info/WHEEL
trident_test-0.1.1.dist-info/entry_points.txt
trident_test-0.1.1.dist-info/RECORD
